rusty_email_validator-0.1.0.dist-info/METADATA
rusty_email_validator-0.1.0.dist-info/WHEEL
rusty_email_validator/__init__.py
rusty_email_validator/py.typed
rusty_email_validator/__init__.pyi
rusty_email_validator/_email_validator.cpython-312-x86_64-linux-gnu.so
rusty_email_validator-0.1.0.dist-info/RECORD
