Metadata-Version: 2.3
Name: rusty-email-validator
Version: 0.1.0
Classifier: Programming Language :: Rust
Classifier: Programming Language :: Python :: Implementation :: CPython
Classifier: Programming Language :: Python :: Implementation :: PyPy
Classifier: License :: OSI Approved :: MIT License
Classifier: Operating System :: OS Independent
Keywords: rust,email,validation
Author-email: Iorio Markus <mbalzert@gmail.com>
Requires-Python: >=3.8
